beanpy/__init__.py
beanpy/definition.py
beanpy/exception.py
beanpy/factory.py
beanpy/processor.py
beanpy/wrapper.py
beanpy-0.0.1.dist-info/licenses/LICENSE
beanpy-0.0.1.dist-info/METADATA
beanpy-0.0.1.dist-info/WHEEL
beanpy-0.0.1.dist-info/top_level.txt
beanpy-0.0.1.dist-info/RECORD
