Metadata-Version: 2.4
Name: beanpy
Version: 0.0.1
Summary: BeanPy 是一个轻量级的 Python 依赖注入框架，通过控制反转（IoC）模式管理对象的创建与依赖关系，支持单例/非单例模式、懒加载、生命周期管理及循环依赖处理，能有效降低代码耦合度，提升可维护性。
Author-email: 黑米拌饭 <heimibanfan@163.com>
License-Expression: MIT
Project-URL: Homepage, https://gitee.com/luanet/bean-py
Classifier: Programming Language :: Python :: 3
Classifier: Operating System :: OS Independent
Requires-Python: >=3.10
License-File: LICENSE
Dynamic: license-file
